{
  "b922ec0e-790f-4e43-aba3-cb549639fff6": {
    "id": "b922ec0e-790f-4e43-aba3-cb549639fff6",
    "status": "completed",
    "progress": 100,
    "message": "Processing complete!",
    "input_file": "uploads/b7019d21_Andrew_Tate_Talking_About_Alcohol.mp4",
    "output_dir": "output/b922ec0e-790f-4e43-aba3-cb549639fff6",
    "options": {
      "clips": 2,
      "platform": "instagram",
      "quality": "high",
      "min_duration": null,
      "max_duration": null,
      "enhance_audio": false,
      "smart_selection": false
    },
    "created_at": "2025-12-28T15:51:48.282911",
    "output_files": [
      {
        "filename": "clip_1_instagram.mp4",
        "url": "/api/download/b922ec0e-790f-4e43-aba3-cb549639fff6/clip_1_instagram.mp4",
        "size": 4706529
      },
      {
        "filename": "clip_2_instagram.mp4",
        "url": "/api/download/b922ec0e-790f-4e43-aba3-cb549639fff6/clip_2_instagram.mp4",
        "size": 2609968
      }
    ],
    "updated_at": "2025-12-28T15:52:10.377604",
    "completed_at": "2025-12-28T15:52:10.377529"
  }
}